kernelpatch/__init__.py
kernelpatch/__main__.py
kernelpatch/config.py
kernelpatch/find.py
kernelpatch/instructions.py
kernelpatch/patch.py
kernelpatch/patterns.py
kernelpatch/utils.py
pykernelpatch-1.1.4.dist-info/LICENSE
pykernelpatch-1.1.4.dist-info/METADATA
pykernelpatch-1.1.4.dist-info/WHEEL
pykernelpatch-1.1.4.dist-info/RECORD
