Metadata-Version: 2.1
Name: pykernelpatch
Version: 1.1.4
Summary: iOS kernelcache patcher
Home-page: https://github.com/Merculous/PyKernelPatch
License: MIT
Author: Merculous
Author-email: 24739823+Merculous@users.noreply.github.com
Requires-Python: >=3.11,<4.0
Classifier: License :: OSI Approved :: MIT License
Classifier: Programming Language :: Python :: 3
Classifier: Programming Language :: Python :: 3.11
Classifier: Programming Language :: Python :: 3.12
Requires-Dist: capstone (>=5.0.1,<6.0.0)
Requires-Dist: pybinpatch (>=1.0.1,<2.0.0)
Project-URL: Repository, https://github.com/Merculous/PyKernelPatch
